fastapicliultra/__init__.py
fastapicliultra/fastapicliultra.py
fastapicliultra/init.py
fastapicliultra-0.1.1.dist-info/METADATA
fastapicliultra-0.1.1.dist-info/WHEEL
fastapicliultra-0.1.1.dist-info/entry_points.txt
fastapicliultra-0.1.1.dist-info/RECORD
