Metadata-Version: 2.3
Name: fastapicliultra
Version: 0.1.1
Summary: Build Fullstack APP with FASTAPI on the go
License: MIT
Author: Khent khentmark27dahay@gmail.com
Requires-Python: >=3.10
Classifier: License :: OSI Approved :: MIT License
Classifier: Programming Language :: Python :: 3
Classifier: Programming Language :: Python :: 3.10
Classifier: Programming Language :: Python :: 3.11
Classifier: Programming Language :: Python :: 3.12
Classifier: Programming Language :: Python :: 3.13
Requires-Dist: click (>=8.1.7,<9.0.0)
